libretranslate/__init__.py
libretranslate/api_keys.py
libretranslate/app.py
libretranslate/default_values.py
libretranslate/detect.py
libretranslate/flood.py
libretranslate/init.py
libretranslate/language.py
libretranslate/locales.py
libretranslate/main.py
libretranslate/manage.py
libretranslate/no_limiter.py
libretranslate/remove_translated_files.py
libretranslate/scheduler.py
libretranslate/secret.py
libretranslate/security.py
libretranslate/storage.py
libretranslate/suggestions.py
libretranslate/locales/.gitignore
libretranslate/locales/ar/meta.json
libretranslate/locales/ar/LC_MESSAGES/messages.mo
libretranslate/locales/ar/LC_MESSAGES/messages.po
libretranslate/locales/az/meta.json
libretranslate/locales/az/LC_MESSAGES/messages.mo
libretranslate/locales/az/LC_MESSAGES/messages.po
libretranslate/locales/be/meta.json
libretranslate/locales/be/LC_MESSAGES/messages.mo
libretranslate/locales/be/LC_MESSAGES/messages.po
libretranslate/locales/bg/meta.json
libretranslate/locales/bg/LC_MESSAGES/messages.mo
libretranslate/locales/bg/LC_MESSAGES/messages.po
libretranslate/locales/bn/meta.json
libretranslate/locales/bn/LC_MESSAGES/messages.mo
libretranslate/locales/bn/LC_MESSAGES/messages.po
libretranslate/locales/ca/meta.json
libretranslate/locales/ca/LC_MESSAGES/messages.mo
libretranslate/locales/ca/LC_MESSAGES/messages.po
libretranslate/locales/ckb/LC_MESSAGES/messages.mo
libretranslate/locales/ckb/LC_MESSAGES/messages.po
libretranslate/locales/cs/meta.json
libretranslate/locales/cs/LC_MESSAGES/messages.mo
libretranslate/locales/cs/LC_MESSAGES/messages.po
libretranslate/locales/cv/LC_MESSAGES/messages.mo
libretranslate/locales/cv/LC_MESSAGES/messages.po
libretranslate/locales/da/meta.json
libretranslate/locales/da/LC_MESSAGES/messages.mo
libretranslate/locales/da/LC_MESSAGES/messages.po
libretranslate/locales/de/meta.json
libretranslate/locales/de/LC_MESSAGES/messages.mo
libretranslate/locales/de/LC_MESSAGES/messages.po
libretranslate/locales/el/meta.json
libretranslate-1.8.3.dist-info/METADATA
libretranslate-1.8.3.dist-info/WHEEL
libretranslate-1.8.3.dist-info/entry_points.txt
libretranslate-1.8.3.dist-info/licenses/LICENSE
libretranslate-1.8.3.dist-info/RECORD
