Metadata-Version: 2.4
Name: libretranslate
Version: 1.8.3
Summary: Free and Open Source Machine Translation API. Self-hosted, no limits, no ties to proprietary services.
Project-URL: Homepage, https://libretranslate.com
Project-URL: Source, https://github.com/LibreTranslate/LibreTranslate
Project-URL: Documentation, https://github.com/LibreTranslate/LibreTranslate
Project-URL: Tracker, https://github.com/LibreTranslate/LibreTranslate/issues
Project-URL: History, https://github.com/LibreTranslate/LibreTranslate/releases
Author: LibreTranslate Authors
Author-email: Piero Toffanin <pt@uav4geo.com>
Maintainer: LibreTranslate Authors
Maintainer-email: Piero Toffanin <pt@uav4geo.com>
License:                     GNU AFFERO GENERAL PUBLIC LICENSE
License-File: LICENSE
Keywords: API,Python,Translate,Translation
Classifier: License :: OSI Approved :: GNU Affero General Public License v3
Classifier: Operating System :: OS Independent
Classifier: Programming Language :: Python :: 3
Classifier: Programming Language :: Python :: 3.8
Classifier: Programming Language :: Python :: 3.9
Classifier: Programming Language :: Python :: 3.10
Classifier: Programming Language :: Python :: 3.11
Classifier: Programming Language :: Python :: 3.12
Classifier: Programming Language :: Python :: 3.13
Requires-Python: >=3.8
Requires-Dist: appdirs==1.4.4
Requires-Dist: apscheduler==3.9.1.post1
Requires-Dist: argos-translate-files==1.4.0
Requires-Dist: argostranslate==1.9.6
Requires-Dist: expiringdict==1.2.2
Requires-Dist: flask-babel==3.1.0
Requires-Dist: flask-limiter==2.6.3
Requires-Dist: flask-swagger-ui==4.11.1
Requires-Dist: flask-swagger==0.2.14
Requires-Dist: flask==2.2.5
Requires-Dist: itsdangerous==2.1.2
Requires-Dist: langdetect==1.0.9
Requires-Dist: lexilang==1.0.6
Requires-Dist: morfessor==2.0.6
Requires-Dist: numpy<2; python_version <= '3.12'
Requires-Dist: numpy==2.3.5; python_version >= '3.13'
Requires-Dist: packaging==23.1
Requires-Dist: polib==1.1.1
Requires-Dist: prometheus-client==0.15.0
Requires-Dist: redis==4.4.4
Requires-Dist: requests==2.31.0
Requires-Dist: torch==2.4.0; python_version < '3.12'
Requires-Dist: torch>=2.5.0; python_version >= '3.12'
Requires-Dist: translatehtml==1.5.2
Requires-Dist: waitress==2.1.2
Requires-Dist: werkzeug==2.3.8
Provides-Extra: test
Requires-Dist: pip-audit; extra == 'test'
Requires-Dist: pre-commit>=3.0.0; extra == 'test'
Requires-Dist: pytest-cov; extra == 'test'
Requires-Dist: pytest>=7.2.0; extra == 'test'
Requires-Dist: types-requests; extra == 'test'
